odxtools_porsche/__init__.py
odxtools_porsche/__main__.py
odxtools_porsche/additionalaudience.py
odxtools_porsche/addressing.py
odxtools_porsche/admindata.py
odxtools_porsche/audience.py
odxtools_porsche/basecomparam.py
odxtools_porsche/basevariantpattern.py
odxtools_porsche/basicstructure.py
odxtools_porsche/codec.py
odxtools_porsche/commrelation.py
odxtools_porsche/commrelationvaluetype.py
odxtools_porsche/companydata.py
odxtools_porsche/companydocinfo.py
odxtools_porsche/companyrevisioninfo.py
odxtools_porsche/companyspecificinfo.py
odxtools_porsche/comparam.py
odxtools_porsche/comparaminstance.py
odxtools_porsche/comparamspec.py
odxtools_porsche/comparamsubset.py
odxtools_porsche/complexcomparam.py
odxtools_porsche/complexdop.py
odxtools_porsche/compositecodec.py
odxtools_porsche/createanycomparam.py
odxtools_porsche/createanydiagcodedtype.py
odxtools_porsche/database.py
odxtools_porsche/dataobjectproperty.py
odxtools_porsche/decodestate.py
odxtools_porsche/description.py
odxtools_porsche/determinenumberofitems.py
odxtools_porsche/diagclasstype.py
odxtools_porsche/diagcodedtype.py
odxtools_porsche/diagcomm.py
odxtools_porsche/diagdatadictionaryspec.py
odxtools_porsche/diaglayercontainer.py
odxtools_porsche/diagnostictroublecode.py
odxtools_porsche/diagservice.py
odxtools_porsche/diagvariable.py
odxtools_porsche/docrevision.py
odxtools_porsche/dopbase.py
odxtools_porsche/dtcconnector.py
odxtools_porsche/dtcdop.py
odxtools_porsche/dynamicendmarkerfield.py
odxtools_porsche/dynamiclengthfield.py
odxtools_porsche/dyndefinedspec.py
odxtools_porsche/dynenddopref.py
odxtools_porsche/dyniddefmodeinfo.py
odxtools_porsche/ecuvariantpattern.py
odxtools_porsche/element.py
odxtools_porsche/encodestate.py
odxtools_porsche/encoding.py
odxtools_porsche/endofpdufield.py
odxtools_porsche/envdataconnector.py
odxtools_porsche/environmentdata.py
odxtools_porsche/environmentdatadescription.py
odxtools_porsche/exceptions.py
odxtools_porsche/externalaccessmethod.py
odxtools_porsche-0.0.2.dist-info/licenses/LICENSE
odxtools_porsche-0.0.2.dist-info/METADATA
odxtools_porsche-0.0.2.dist-info/WHEEL
odxtools_porsche-0.0.2.dist-info/entry_points.txt
odxtools_porsche-0.0.2.dist-info/top_level.txt
odxtools_porsche-0.0.2.dist-info/RECORD
